jsrl_library_common/__init__.py
jsrl_library_common/constants/__init__.py
jsrl_library_common/constants/swagger/__init__.py
jsrl_library_common/constants/swagger/swagger_constants.py
jsrl_library_common/constants/swagger/swagger_security_schemas.py
jsrl_library_common/exceptions/__init__.py
jsrl_library_common/exceptions/files/files_exceptions.py
jsrl_library_common/models/__init__.py
jsrl_library_common/models/swagger/__init__.py
jsrl_library_common/models/swagger/flask_swagger_blueprint.py
jsrl_library_common/models/swagger/flask_swagger_models.py
jsrl_library_common/models/swagger/singleton.py
jsrl_library_common/models/swagger/swagger_doc.py
jsrl_library_common/schemas/__init__.py
jsrl_library_common/schemas/swagger/__init__.py
jsrl_library_common/schemas/swagger/swagger_hal_schemas.py
jsrl_library_common/schemas/swagger/swagger_schemas.py
jsrl_library_common/utils/__init__.py
jsrl_library_common/utils/data/__init__.py
jsrl_library_common/utils/data/files.py
jsrl_library_common/utils/data/yaml.py
jsrl_library_common/utils/swagger/__init__.py
jsrl_library_common/utils/swagger/swagger_file.py
jsrl_library_common/utils/swagger/swagger_representers.py
jsrl_library_common_swagger-0.0.1.dist-info/METADATA
jsrl_library_common_swagger-0.0.1.dist-info/WHEEL
jsrl_library_common_swagger-0.0.1.dist-info/top_level.txt
jsrl_library_common_swagger-0.0.1.dist-info/RECORD
