Metadata-Version: 2.2
Name: jsrl_library_common_swagger
Version: 0.0.1
Home-page: 
Download-URL: 
Author: Juan Sebastian Reyes Leyton
Author-email: sebas.reyes2002@hotmail.com
License: Copyright
Keywords: jsrl_library_common_swagger
Platform: Unix
Classifier: Environment :: Console
Classifier: Intended Audience :: Developers
Classifier: Topic :: Software Development :: Libraries
Classifier: Programming Language :: Python
Classifier: Programming Language :: Python :: 3.11
Classifier: Operating System :: OS Independent
Requires-Dist: PyYAML==6.0.2
Dynamic: author
Dynamic: author-email
Dynamic: classifier
Dynamic: keywords
Dynamic: license
Dynamic: platform
Dynamic: requires-dist
